seeed_si114x.py
seeed_si115x.py
seeed_python_si114x-1.1.0.dist-info/LICENSE
seeed_python_si114x-1.1.0.dist-info/METADATA
seeed_python_si114x-1.1.0.dist-info/WHEEL
seeed_python_si114x-1.1.0.dist-info/entry_points.txt
seeed_python_si114x-1.1.0.dist-info/top_level.txt
seeed_python_si114x-1.1.0.dist-info/RECORD
