Metadata-Version: 2.1
Name: seeed-python-si114x
Version: 1.1.0
Summary: Python library for the Grove - Sunlight Sensor (si114x,si115x). 
Home-page: https://github.com/Seeed-Studio/Seeed_Python_SI114X
Author: Hansen
Author-email: 595355940@qq.com
License: MIT
Keywords: seeed grove si114x si115x sensor i2c hardware
Classifier: Development Status :: 3 - Alpha
Classifier: Intended Audience :: Developers
Classifier: Topic :: Software Development :: Libraries
Classifier: Topic :: System :: Hardware
Classifier: License :: OSI Approved :: MIT License
Classifier: Programming Language :: Python :: 3
Classifier: Programming Language :: Python :: 3.4
Classifier: Programming Language :: Python :: 3.5
License-File: LICENSE
Requires-Dist: Seeed-grove.py
